Metadata-Version: 1.0
Name: attics
Version: 0.0.1
Summary: Attics project TBD
Home-page: UNKNOWN
Author: Ruslan
Author-email: r@gmail.com
License: LICENSE.txt
Platform: UNKNOWN
